tests/__init__.py
tests/test_iterables.py
uuuu/__init__.py
uuuu/iterables.py
uuuu-0.0.1.dist-info/LICENSE
uuuu-0.0.1.dist-info/METADATA
uuuu-0.0.1.dist-info/WHEEL
uuuu-0.0.1.dist-info/top_level.txt
uuuu-0.0.1.dist-info/RECORD
